{
"pozecorno":{
    "name":"pzPB.png",
    "x":-15001,
    "y":-10001,
    "width":284,
    "height":188
        },
"sususu":{
    "name":"sus.png",
    "x":-143,
    "y":-193,
    "width":137,
    "height":149
        },
"Mega_Flag":{
    "name":"Mega_Flag_2.2.png",
    "x":-9507,
    "y":2128,
    "width":1943,
    "height":1161
        },
"demoninhos_MAR":{
    "name":"demoninhos.png",
    "x":-13678,
    "y":20132,
    "width":364,
    "height":408
        },
"diabin":{
    "name":"diabin.png",
    "x":-15083,
    "y":21320,
    "width":217,
    "height":171
        },
"anime":{
    "name":"anime.png",
    "x":-15832,
    "y":21633,
    "width":399,
    "height":376
        },
"AyudaGrecia":{
    "name":"Grecia_1.png",
    "x":3781,
    "y":-8022,
    "width":355,
    "height":59
        },
 "ilha":{
    "name":"ilha.png",
    "x":-13744,
    "y":19633,
    "width":350,
    "height":526
        },
 "sharingan":{
    "name":"sharingan.png",
    "x":-15019,
    "y":22192,
    "width":351,
    "height":351
        },
 "homi":{
    "name":"homi.png",
    "x":-15954,
    "y":20627,
    "width":332,
    "height":331
        },
    "Basecima":{
    "name":"nuvemcima.png",
    "x":-14897,
    "y":20041,
    "width":1360,
    "height":1888
        },
 "everton":{
    "name":"bahiafz.png",
    "x":-7501,
    "y":2157,
    "width":365,
    "height":242
        },
 "Flag":{
    "name":"Flag.png",
    "x":-18114,
    "y":-22989,
    "width":141,
    "height":81
        },
 "Flag2":{
    "name":"Flag2.png",
    "x":-18042,
    "y":-23452,
    "width":153,
    "height":119
        },
 "Bola":{
    "name":"Bola.png",
    "x":-18053,
    "y":-23285,
    "width":185,
    "height":219
        },
 "Alce":{
    "name":"Alce.png",
    "x":-17965,
    "y":-23039,
    "width":110,
    "height":129
        },
 "Alce2":{
    "name":"Alce2.png",
    "x":-17960,
    "y":-22902,
    "width":155,
    "height":184
        },
 "Brasao":{
    "name":"Brasao.png",
    "x":-18340,
    "y":-23460,
    "width":196,
    "height":188
        },
 "Cross":{
    "name":"Cross.png",
    "x":-18089,
    "y":-22838,
    "width":95,
    "height":134
        },
 "MulherImensa":{
    "name":"major2.png",
    "x":-15594,
    "y":20926,
    "width":457,
    "height":656
        },
 "Corna":{
    "name":"corna.png",
    "x":-15063,
    "y":21740,
    "width":400,
    "height":440
         }
 
 

}
